{
  "matriz": { "filas": 20, "columnas": 20 },
  "origen": [0, 0],
  "destino": [19, 19],
  "agujerosNegros": [
    [2, 3], [4, 7], [6, 1], [8, 10], [10, 5], [1, 9], [3, 6], [5, 2], [7, 8], [9, 4], [11, 3], [0, 10], [8, 2], [2, 9], [6, 11],
    [12, 13], [13, 2], [14, 7], [7, 13], [5, 10], [10, 12], [3, 12], [12, 5], [8, 7], [9, 11], [13, 8], [11, 14], [4, 13], [1, 12], [6, 14], [14, 1],
    [15, 15], [16, 3], [17, 17], [18, 8], [19, 5], [15, 7], [16, 12], [17, 2], [18, 14], [19, 10]
  ],
  "estrellasGigantes": [
    [1, 2], [3, 8], [5, 5], [7, 1], [9, 9], [11, 7], [13, 13], [2, 12], [15, 18], [18, 19]
  ],
  "agujerosGusano": [
    { "entrada": [0, 10], "salida": [19, 0] },
    { "entrada": [5, 19], "salida": [10, 1] },
    { "entrada": [7, 3], "salida": [2, 18] },
    { "entrada": [12, 12], "salida": [18, 2] }
  ],
  "zonasRecarga": [ [2, 5, 2], [6, 6, 3], [10, 10, 2], [13, 3, 2], [17, 17, 2] ],
  "celdasCargaRequerida": [
    { "coordenada": [3, 3], "cargaGastada": 10 },
    { "coordenada": [7, 7], "cargaGastada": 15 },
    { "coordenada": [9, 2], "cargaGastada": 12 },
    { "coordenada": [12, 12], "cargaGastada": 18 },
    { "coordenada": [18, 18], "cargaGastada": 20 }
  ],
  "cargaInicial": 80,
  "matrizInicial": [
    [2,1,3,2,4,1,2,3,4,2,1,3,2,4,1,2,3,4,2,1],
    [3,2,1,4,2,3,1,2,3,4,2,1,3,2,4,1,2,3,4,2],
    [4,3,2,1,3,2,4,1,2,3,1,4,2,3,1,4,2,3,1,4],
    [1,4,3,2,1,4,2,3,1,4,3,2,1,4,3,2,1,4,3,2],
    [2,1,4,3,2,1,3,4,2,1,4,3,2,1,4,3,2,1,4,3],
    [3,2,1,4,3,2,1,4,3,2,1,4,3,2,1,4,3,2,1,4],
    [4,3,2,1,4,3,2,1,4,3,2,1,4,3,2,1,4,3,2,1],
    [1,4,3,2,1,4,3,2,1,4,3,2,1,4,3,2,1,4,3,2],
    [2,1,4,3,2,1,4,3,2,1,4,3,2,1,4,3,2,1,4,3],
    [3,2,1,4,3,2,1,4,3,2,1,4,3,2,1,4,3,2,1,4],
    [4,3,2,1,4,3,2,1,4,3,2,1,4,3,2,1,4,3,2,1],
    [1,4,3,2,1,4,3,2,1,4,3,2,1,4,3,2,1,4,3,2],
    [2,1,4,3,2,1,4,3,2,1,4,3,2,1,4,3,2,1,4,3],
    [3,2,1,4,3,2,1,4,3,2,1,4,3,2,1,4,3,2,1,4],
    [4,3,2,1,4,3,2,1,4,3,2,1,4,3,2,1,4,3,2,1],
    [1,4,3,2,1,4,3,2,1,4,3,2,1,4,3,2,1,4,3,2],
    [2,1,4,3,2,1,4,3,2,1,4,3,2,1,4,3,2,1,4,3],
    [3,2,1,4,3,2,1,4,3,2,1,4,3,2,1,4,3,2,1,4],
    [4,3,2,1,4,3,2,1,4,3,2,1,4,3,2,1,4,3,2,1],
    [1,4,3,2,1,4,3,2,1,4,3,2,1,4,3,2,1,4,3,2]
  ]
}